objectprogramming-105.data/data/op/mod/__init__.py
objectprogramming-105.data/data/op/mod/dbg.py
objectprogramming-105.data/data/op/mod/irc.py
objectprogramming-105.data/data/op/mod/mbx.py
objectprogramming-105.data/data/op/mod/rss.py
objectprogramming-105.data/data/op/mod/udp.py
objectprogramming-105.data/data/share/doc/op/README.rst
objectprogramming-105.data/scripts/op
op/__init__.py
op/handler.py
op/message.py
op/objects.py
op/running.py
op/threads.py
op/usersdb.py
op/version.py
objectprogramming-105.dist-info/METADATA
objectprogramming-105.dist-info/WHEEL
objectprogramming-105.dist-info/top_level.txt
objectprogramming-105.dist-info/RECORD
