Metadata-Version: 2.1
Name: objectprogramming
Version: 105
Summary: functional programming with objects
Home-page: http://github.com/operbot/objectprogramming
Author: Bart Thate
Author-email: operbot100@gmail.com
License: Public Domain
Platform: UNKNOWN
Classifier: Development Status :: 4 - Beta
Classifier: License :: Public Domain
Classifier: Operating System :: POSIX :: Linux
Classifier: Programming Language :: Python :: 3 :: Only
Classifier: Programming Language :: Python
Classifier: Intended Audience :: System Administrators
Classifier: Topic :: Communications :: Chat :: Internet Relay Chat
Classifier: Topic :: Software Development :: Libraries :: Python Modules
